{
  "date": "2025-09-25",
  "region": "Mi\u1EC1n Nam",
  "prizes": [
    {
      "province": "T\u00E2y Ninh",
      "data": [
        {
          "g8": [
            "71"
          ],
          "g7": [
            "397"
          ],
          "g6": [
            "5153",
            "0271",
            "9798"
          ],
          "g5": [
            "0313"
          ],
          "g4": [
            "10752",
            "66514",
            "22447",
            "64069",
            "00293",
            "48846",
            "93773"
          ],
          "g3": [
            "66636",
            "17208"
          ],
          "g2": [
            "21002"
          ],
          "g1": [
            "87765"
          ],
          "db": [
            "068430"
          ]
        }
      ]
    },
    {
      "province": "An Giang",
      "data": [
        {
          "g8": [
            "16"
          ],
          "g7": [
            "581"
          ],
          "g6": [
            "2991",
            "9716",
            "6943"
          ],
          "g5": [
            "6013"
          ],
          "g4": [
            "62443",
            "51711",
            "32865",
            "31265",
            "22811",
            "14171",
            "30103"
          ],
          "g3": [
            "40699",
            "47669"
          ],
          "g2": [
            "76586"
          ],
          "g1": [
            "92632"
          ],
          "db": [
            "107952"
          ]
        }
      ]
    },
    {
      "province": "B\u00ECnh Thu\u1EADn",
      "data": [
        {
          "g8": [
            "13"
          ],
          "g7": [
            "370"
          ],
          "g6": [
            "1740",
            "9976",
            "5650"
          ],
          "g5": [
            "3432"
          ],
          "g4": [
            "62529",
            "07996",
            "37256",
            "20500",
            "25719",
            "59666",
            "21392"
          ],
          "g3": [
            "41224",
            "64933"
          ],
          "g2": [
            "59812"
          ],
          "g1": [
            "30366"
          ],
          "db": [
            "032820"
          ]
        }
      ]
    }
  ]
}